{"address1": "150-20, Gongse-ro", "address2": "Giheung-gu", "city": "Yongin-Si", "country": "South Korea", "phone": "82 31 8006 3100", "fax": "82 3 1210 7887", "website": "https://www.samsungsdi.com", "industry": "Electronic Components", "industryKey": "electronic-components", "industryDisp": "Electronic Components", "sector": "Technology", "sectorKey": "technology", "sectorDisp": "Technology", "longBusinessSummary": "Samsung SDI Co., Ltd. manufactures and sells batteries in South Korea, Europe, China, North America, Southeast Asia, and internationally. The company operates through Energy Solutions and Electronic Materials segments. It offers small-sized lithium ion batteries used in laptops, tablets, mobile phones, wearable devices, power banks, power tools, garden tools, vacuum cleaners, e-bikes, e-scooters, and ignition products; automotive batteries; and energy storage systems for use in residential, utility, commercial, UPS, and base transceiver station applications. In addition, the company provides electronic materials, including semiconductor products, such as spin-on hardmasks, spin-on dielectrics, and epoxy molding compounds; LCD products, such as polarizing films and color photo resist products; and OLED products comprising evaporation materials and thin film encapsulation products. Further, it manufactures and sells rechargeable battery raw materials; and invests in new technology venture business. Samsung SDI Co., Ltd. was incorporated in 1970 and is headquartered in Yongin, South Korea.", "companyOfficers": [{"maxAge": 1, "name": "Mr. HyunJun  Young", "age": 63, "title": "Executive Chairman of the Board", "yearBorn": 1960, "exercisedValue": 0, "unexercisedValue": 0}, {"maxAge": 1, "name": "Mr. Ho Choi  Yoon", "age": 60, "title": "President, CEO & Executive Director", "yearBorn": 1963, "exercisedValue": 0, "unexercisedValue": 0}, {"maxAge": 1, "name": "Mr. Sung Kim  Jong", "title": "Executive VP of Business Management Office, CFO & Executive Director", "exercisedValue": 0, "unexercisedValue": 0}, {"maxAge": 1, "name": "Ike  Kim", "title": "Vice President of Finance & Accounting Team", "exercisedValue": 0, "unexercisedValue": 0}, {"maxAge": 1, "name": "Mr. Chun  Dongrak", "title": "Chief Risk Officer, Head of HR Team and Executive Vice President", "exercisedValue": 0, "unexercisedValue": 0}, {"maxAge": 1, "name": "Michael  Son", "title": "Senior Vice President of Battery - Marketing", "exercisedValue": 0, "unexercisedValue": 0}, {"maxAge": 1, "name": "Kwangsung  Kim", "title": "Head of the Electronic Materials Servicing Marketing Team", "exercisedValue": 0, "unexercisedValue": 0}, {"maxAge": 1, "name": "Heonjoon  Kim", "title": "Head of Battery Marketing Service Group", "exercisedValue": 0, "unexercisedValue": 0}, {"maxAge": 1, "name": "Jae-Young  Lee", "title": "Executive Vice President of Battery Business", "exercisedValue": 0, "unexercisedValue": 0}, {"maxAge": 1, "name": "Hanjae  Cho", "title": "Executive Vice President for Small Battery", "exercisedValue": 0, "unexercisedValue": 0}], "auditRisk": 1, "boardRisk": 3, "compensationRisk": 1, "shareHolderRightsRisk": 1, "overallRisk": 2, "governanceEpochDate": 1709251200, "maxAge": 86400, "priceHint": 2, "previousClose": 455500.0, "open": 454500.0, "dayLow": 453500.0, "dayHigh": 467000.0, "regularMarketPreviousClose": 455500.0, "regularMarketOpen": 454500.0, "regularMarketDayLow": 453500.0, "regularMarketDayHigh": 467000.0, "dividendRate": 1000.0, "dividendYield": 0.0022, "exDividendDate": 1703635200, "payoutRatio": 0.033299997, "fiveYearAvgDividendYield": 0.23, "beta": 0.842, "volume": 118381, "regularMarketVolume": 118381, "averageVolume": 446481, "averageVolume10days": 1032204, "averageDailyVolume10Day": 1032204, "bid": 462500.0, "ask": 463000.0, "marketCap": 30700294111232, "fiftyTwoWeekLow": 342000.0, "fiftyTwoWeekHigh": 787000.0, "priceToSalesTrailing12Months": 1.3519416, "fiftyDayAverage": 396080.0, "twoHundredDayAverage": 516252.5, "currency": "KRW", "enterpriseValue": 35528653144064, "forwardPE": 13.039369, "profitMargins": 0.088479996, "floatShares": 53404486, "sharesOutstanding": 65433100, "heldPercentInsiders": 0.20414, "heldPercentInstitutions": 0.4104, "impliedSharesOutstanding": 67275200, "lastFiscalYearEnd": 1703980800, "nextFiscalYearEnd": 1735603200, "mostRecentQuarter": 1703980800, "earningsQuarterlyGrowth": -0.175, "netIncomeToCommon": 2009207144448, "pegRatio": 2.34, "enterpriseToRevenue": 1.565, "enterpriseToEbitda": 10.57, "52WeekChange": -0.3927614, "SandP52WeekChange": 0.32311738, "lastDividendValue": 1000.0, "lastDividendDate": 1703635200, "exchange": "KSC", "quoteType": "EQUITY", "symbol": "006400.KS", "underlyingSymbol": "006400.KS", "shortName": "SAMSUNG SDI CO.,LTD.", "longName": "Samsung SDI Co., Ltd.", "firstTradeDateEpochUtc": 946944000, "timeZoneFullName": "Asia/Seoul", "timeZoneShortName": "KST", "uuid": "2ffa77b3-e8ea-355f-b4bd-ed4aadc7766f", "messageBoardId": "finmb_878475", "gmtOffSetMilliseconds": 32400000, "currentPrice": 463500.0, "targetHighPrice": 928000.0, "targetLowPrice": 310000.0, "targetMeanPrice": 611654.0, "targetMedianPrice": 595000.0, "recommendationMean": 1.8, "recommendationKey": "buy", "numberOfAnalystOpinions": 26, "totalCash": 2126559838208, "totalCashPerShare": 31800.15, "ebitda": 3361340653568, "totalDebt": 5798852820992, "quickRatio": 0.619, "currentRatio": 1.078, "totalRevenue": 22708299497472, "debtToEquity": 29.129, "revenuePerShare": 339575.38, "returnOnAssets": 0.03175, "returnOnEquity": 0.1113, "freeCashflow": -1543985954816, "operatingCashflow": 2103521574912, "earningsGrowth": -0.121, "revenueGrowth": -0.067, "grossMargins": 0.17535, "ebitdaMargins": 0.14802, "operatingMargins": 0.05603, "financialCurrency": "KRW", "trailingPegRatio": 8.7951}