{"address1": "Bahnhofstrasse 36", "city": "Zurich", "zip": "8010", "country": "Switzerland", "phone": "41 58 888 1111", "fax": "41 58 888 5517", "website": "https://www.juliusbaer.com", "industry": "Asset Management", "industryKey": "asset-management", "industryDisp": "Asset Management", "sector": "Financial Services", "sectorKey": "financial-services", "sectorDisp": "Financial Services", "longBusinessSummary": "Julius B\u00e4r Gruppe AG provides wealth management solutions in Switzerland, Europe, the Americas, Asia, and internationally. The company offers investment advisory and discretionary mandates; structured products, securities execution and advisory, private markets and fund offering; wealth planning, family office services; asset servicing, and lombard lending solutions. It also provides open product platform solutions. Julius B\u00e4r Gruppe AG was founded in 1890 and is headquartered in Zurich, Switzerland.", "fullTimeEmployees": 7425, "companyOfficers": [{"maxAge": 1, "name": "Mr. Nic  Dreckmann", "age": 49, "title": "COO, Head of Intermediaries, CEO & Member of Executive Board", "yearBorn": 1974, "fiscalYear": 2023, "totalPay": 1996000, "exercisedValue": 0, "unexercisedValue": 0}, {"maxAge": 1, "name": "Ms. Evangelia  Kostakis", "age": 47, "title": "CFO & Member of the Executive Board", "yearBorn": 1976, "fiscalYear": 2023, "exercisedValue": 0, "unexercisedValue": 0}], "auditRisk": 10, "boardRisk": 1, "compensationRisk": 1, "shareHolderRightsRisk": 1, "overallRisk": 2, "governanceEpochDate": 1709251200, "compensationAsOfEpochDate": 1703980800, "maxAge": 86400, "priceHint": 2, "previousClose": 49.55, "open": 50.46, "dayLow": 50.26, "dayHigh": 52.08, "regularMarketPreviousClose": 49.55, "regularMarketOpen": 50.46, "regularMarketDayLow": 50.26, "regularMarketDayHigh": 52.08, "dividendRate": 2.6, "dividendYield": 0.0525, "exDividendDate": 1713139200, "payoutRatio": 0.52099997, "fiveYearAvgDividendYield": 3.9, "beta": 1.29, "trailingPE": 10.36473, "forwardPE": 9.33574, "volume": 1295864, "regularMarketVolume": 1295864, "averageVolume": 764857, "averageVolume10days": 812126, "averageDailyVolume10Day": 812126, "bid": 51.72, "ask": 52.1, "marketCap": 10578291712, "fiftyTwoWeekLow": 42.98, "fiftyTwoWeekHigh": 64.7, "priceToSalesTrailing12Months": 3.2654088, "fiftyDayAverage": 47.8002, "twoHundredDayAverage": 53.04235, "trailingAnnualDividendRate": 2.6, "trailingAnnualDividendYield": 0.05247225, "currency": "CHF", "enterpriseValue": 4842313216, "profitMargins": 0.14015001, "floatShares": 203809958, "sharesOutstanding": 204530000, "heldPercentInsiders": 0.0052, "heldPercentInstitutions": 0.61169, "impliedSharesOutstanding": 205148992, "bookValue": 30.082, "priceToBook": 1.7193006, "lastFiscalYearEnd": 1703980800, "nextFiscalYearEnd": 1735603200, "mostRecentQuarter": 1703980800, "netIncomeToCommon": 454000000, "trailingEps": 4.99, "forwardEps": 5.54, "pegRatio": 2.3, "enterpriseToRevenue": 1.495, "52WeekChange": -0.20592946, "SandP52WeekChange": 0.32311738, "lastDividendValue": 2.6, "lastDividendDate": 1713139200, "exchange": "EBS", "quoteType": "EQUITY", "symbol": "BAER.SW", "underlyingSymbol": "BAER.SW", "shortName": "JULIUS BAER N", "longName": "Julius B\u00e4r Gruppe AG", "firstTradeDateEpochUtc": 796892400, "timeZoneFullName": "Europe/Zurich", "timeZoneShortName": "CET", "uuid": "1fc2059d-8e00-3387-ac4b-4d0623118a35", "messageBoardId": "finmb_61027839", "gmtOffSetMilliseconds": 3600000, "currentPrice": 51.72, "targetHighPrice": 65.0, "targetLowPrice": 50.7, "targetMeanPrice": 57.28, "targetMedianPrice": 56.0, "recommendationMean": 2.1, "recommendationKey": "buy", "numberOfAnalystOpinions": 13, "totalCash": 30178099200, "totalCashPerShare": 147.343, "totalDebt": 24869900288, "totalRevenue": 3239500032, "revenuePerShare": 15.754, "returnOnAssets": 0.00448, "returnOnEquity": 0.07283, "operatingCashflow": -929100032, "revenueGrowth": -0.391, "operatingMargins": -0.03619, "financialCurrency": "CHF", "trailingPegRatio": 3.2539}