{"address1": "280 Park Avenue", "city": "New York", "state": "NY", "zip": "10017", "country": "United States", "phone": "212 415 3600", "fax": "212 415 3530", "website": "https://www.omnicomgroup.com", "industry": "Advertising Agencies", "industryKey": "advertising-agencies", "industryDisp": "Advertising Agencies", "sector": "Communication Services", "sectorKey": "communication-services", "sectorDisp": "Communication Services", "longBusinessSummary": "Omnicom Group Inc., together with its subsidiaries, offers advertising, marketing, and corporate communications services. It provides a range of services in the areas of advertising and media, precision marketing, commerce and branding, experiential, execution and support, public relations, and healthcare. The company's services include advertising, branding, content marketing, corporate social responsibility consulting, crisis communications, custom publishing, data analytics, database management, digital/direct marketing and post-production, digital transformation consulting, entertainment marketing, experiential marketing, field marketing, sales support, financial/corporate business-to-business advertising, graphic arts/digital imaging, healthcare marketing and communications, and instore design services. Its services also comprise interactive marketing, investor relations, marketing research, media planning and buying, retail media planning and buying, merchandising and point of sale, mobile marketing, multi-cultural marketing, non-profit marketing, organizational communications, package design, product placement, promotional marketing, public affairs, public relations, retail marketing, retail media and e-commerce, search engine marketing, shopper marketing, social media marketing, and sports and event marketing services. It operates in the North and Latin America, Europe, the Middle East and Africa (EMEA), and the Asia Pacific. The company was incorporated in 1944 and is based in New York, New York.", "fullTimeEmployees": 75900, "companyOfficers": [{"maxAge": 1, "name": "Mr. John D. Wren", "age": 70, "title": "Chairman & CEO", "yearBorn": 1953, "fiscalYear": 2022, "totalPay": 13179165, "exercisedValue": 0, "unexercisedValue": 0}, {"maxAge": 1, "name": "Mr. Daryl D. Simm", "age": 62, "title": "President & COO", "yearBorn": 1961, "fiscalYear": 2022, "totalPay": 6017120, "exercisedValue": 0, "unexercisedValue": 0}, {"maxAge": 1, "name": "Mr. Jonathan B. Nelson", "age": 55, "title": "Founder & CEO of Omnicom Digital", "yearBorn": 1968, "fiscalYear": 2022, "totalPay": 3259150, "exercisedValue": 0, "unexercisedValue": 0}, {"maxAge": 1, "name": "Mr. Philip J. Angelastro", "age": 58, "title": "Executive VP & CFO", "yearBorn": 1965, "fiscalYear": 2022, "totalPay": 5442185, "exercisedValue": 0, "unexercisedValue": 0}, {"maxAge": 1, "name": "Mr. Thomas W. Watson", "title": "Co-Founder & Vice Chairman Emeritus", "fiscalYear": 2022, "exercisedValue": 0, "unexercisedValue": 0}, {"maxAge": 1, "name": "Mr. Andrew L. Castellaneta", "age": 64, "title": "Senior VP & Chief Accounting Officer", "yearBorn": 1959, "fiscalYear": 2022, "exercisedValue": 0, "unexercisedValue": 0}, {"maxAge": 1, "name": "Mr. Paolo  Yuvienco", "title": "Executive VP & Chief Technology Officer", "fiscalYear": 2022, "exercisedValue": 0, "unexercisedValue": 0}, {"maxAge": 1, "name": "Dr. Craig  Cuyar", "title": "Senior VP & Global Chief Information Officer", "fiscalYear": 2022, "exercisedValue": 0, "unexercisedValue": 0}, {"maxAge": 1, "name": "Mr. Gregory H. Lundberg", "title": "Senior Vice President of Investor Relations", "fiscalYear": 2022, "exercisedValue": 0, "unexercisedValue": 0}, {"maxAge": 1, "name": "Mr. Louis F. Januzzi", "age": 49, "title": "Senior VP, General Counsel & Secretary", "yearBorn": 1974, "fiscalYear": 2022, "exercisedValue": 0, "unexercisedValue": 0}], "auditRisk": 7, "boardRisk": 5, "compensationRisk": 6, "shareHolderRightsRisk": 1, "overallRisk": 2, "governanceEpochDate": 1709251200, "compensationAsOfEpochDate": 1672444800, "maxAge": 86400, "priceHint": 2, "previousClose": 94.26, "open": 94.23, "dayLow": 93.825, "dayHigh": 94.95, "regularMarketPreviousClose": 94.26, "regularMarketOpen": 94.23, "regularMarketDayLow": 93.825, "regularMarketDayHigh": 94.95, "dividendRate": 2.8, "dividendYield": 0.0297, "exDividendDate": 1709856000, "payoutRatio": 0.4052, "fiveYearAvgDividendYield": 3.71, "beta": 0.972, "trailingPE": 13.648335, "forwardPE": 11.240762, "volume": 1130462, "regularMarketVolume": 1130462, "averageVolume": 1611616, "averageVolume10days": 2327320, "averageDailyVolume10Day": 2327320, "bid": 92.7, "ask": 94.41, "bidSize": 800, "askSize": 800, "marketCap": 18672717824, "fiftyTwoWeekLow": 72.2, "fiftyTwoWeekHigh": 99.23, "priceToSalesTrailing12Months": 1.2709272, "fiftyDayAverage": 89.528, "twoHundredDayAverage": 84.3282, "trailingAnnualDividendRate": 2.8, "trailingAnnualDividendYield": 0.02970507, "currency": "USD", "enterpriseValue": 22113193984, "profitMargins": 0.0947, "floatShares": 195880135, "sharesOutstanding": 197992992, "sharesShort": 7223849, "sharesShortPriorMonth": 7670158, "sharesShortPreviousMonthDate": 1706659200, "dateShortInterest": 1709164800, "sharesPercentSharesOut": 0.0365, "heldPercentInsiders": 0.013739999, "heldPercentInstitutions": 0.95849997, "shortRatio": 4.47, "shortPercentOfFloat": 0.042, "impliedSharesOutstanding": 197992992, "bookValue": 18.264, "priceToBook": 5.16371, "lastFiscalYearEnd": 1703980800, "nextFiscalYearEnd": 1735603200, "mostRecentQuarter": 1703980800, "earningsQuarterlyGrowth": -0.01, "netIncomeToCommon": 1391399936, "trailingEps": 6.91, "forwardEps": 8.39, "pegRatio": 0.89, "lastSplitFactor": "2:1", "lastSplitDate": 1182816000, "enterpriseToRevenue": 1.505, "enterpriseToEbitda": 9.531, "52WeekChange": 0.06352246, "SandP52WeekChange": 0.32311738, "lastDividendValue": 0.7, "lastDividendDate": 1709856000, "exchange": "NYQ", "quoteType": "EQUITY", "symbol": "OMC", "underlyingSymbol": "OMC", "shortName": "Omnicom Group Inc.", "longName": "Omnicom Group Inc.", "firstTradeDateEpochUtc": 322151400, "timeZoneFullName": "America/New_York", "timeZoneShortName": "EDT", "uuid": "5dba3e85-8bfe-3a7d-93bb-31e7de3c4774", "messageBoardId": "finmb_96161", "gmtOffSetMilliseconds": -14400000, "currentPrice": 94.31, "targetHighPrice": 117.0, "targetLowPrice": 82.0, "targetMeanPrice": 99.1, "targetMedianPrice": 100.0, "recommendationMean": 2.4, "recommendationKey": "buy", "numberOfAnalystOpinions": 10, "totalCash": 4432000000, "totalCashPerShare": 22.385, "ebitda": 2320199936, "totalDebt": 6858999808, "quickRatio": 0.806, "currentRatio": 0.947, "totalRevenue": 14692200448, "debtToEquity": 147.833, "revenuePerShare": 73.682, "returnOnAssets": 0.04789, "returnOnEquity": 0.33486, "freeCashflow": 1130587520, "operatingCashflow": 1421900032, "earningsGrowth": 0.019, "revenueGrowth": 0.05, "grossMargins": 0.18865, "ebitdaMargins": 0.15792, "operatingMargins": 0.13258, "financialCurrency": "USD", "trailingPegRatio": 1.5049}